dataaccess/__init__.py
dataaccess/articles.py
dataaccess/database.py
contiltcore-0.0.3.dist-info/METADATA
contiltcore-0.0.3.dist-info/WHEEL
contiltcore-0.0.3.dist-info/top_level.txt
contiltcore-0.0.3.dist-info/RECORD
