Metadata-Version: 2.1
Name: contiltcore
Version: 0.0.3
Summary: Contilt Infrastructure
Home-page: https://github.com/your_package/homepage/
Author: Contilt
Author-email: info@contilt.com
License: UNKNOWN
Platform: UNKNOWN
Classifier: Programming Language :: Python :: 3.6
Classifier: License :: OSI Approved :: MIT License
Requires-Dist: PyMySQL (==0.9.3)
Requires-Dist: mysqlclient (==1.4.2)
